{
  "current": {
    "slug": "ai-office-residential-conversion-algorithm",
    "phase": "QA",
    "journalist": "Elena Vasquez",
    "started": "2026-06-21T21:02:00Z",
    "round": 1,
    "critique_scores": {
      "general_editor": 9.0,
      "voice_coach": 9.0,
      "ethics_reviewer": 9.0,
      "social_shareability": 9.0,
      "legal_accuracy": 9.0,
      "research_rigor": 9.0,
      "data_presentation": 9.0
    }
  },
  "last_completed": {
    "article_number": 382,
    "headline": "Your Foundation Guy Checked 2,000 Square Feet With a Ruler. The Laser Finished Before He Uncapped the Chalk.",
    "journalist": "Jake Kowalski",
    "published": "2026-06-21",
    "slug": "ai-foundation-laser-scanning-flatness"
  }
}
