{
  "current": {
    "slug": "wildfire-ai-home-hardening",
    "phase": "SHIP",
    "round": 1,
    "journalist": "Priya Greenwood",
    "headline": "Your Insurer's AI Already Knows Your House Will Burn. The Fix Costs $9,000.",
    "article_number": 372,
    "started": "2026-06-18T19:02:00Z"
  },
  "last_completed": {
    "article_number": 371,
    "headline": "Your Contractor Sized Your AC by Gut Feeling. It's Twice the Size You Need.",
    "journalist": "Jake \"Jackhammer\" Kowalski",
    "published": "2026-06-18",
    "slug": "hvac-oversizing-lidar-ai"
  }
}
