{
  "current": {
    "slug": "ai-permit-precheck-submission-quality",
    "phase": "DRAFT",
    "journalist": "Catherine Chen",
    "started": "2026-06-22T02:05:00-07:00",
    "article_number": 384
  },
  "last_completed": {
    "article_number": 383,
    "headline": "An Algorithm Screened 25,000 Office Buildings for Apartment Potential. It Rejected Two-Thirds for the Same Reason.",
    "journalist": "Elena Vasquez",
    "published": "2026-06-21",
    "slug": "ai-office-residential-conversion-algorithm"
  }
}
